allsql/__init__.py
allsql-0.0.5.dist-info/LICENSE
allsql-0.0.5.dist-info/METADATA
allsql-0.0.5.dist-info/WHEEL
allsql-0.0.5.dist-info/top_level.txt
allsql-0.0.5.dist-info/RECORD
