Metadata-Version: 2.1
Name: allsql
Version: 0.0.5
Summary: Simple alternative to SQLAlchemy(Sqlite and MySql)
Home-page: https://github.com/claudiotorresarbe/allsql
Author: Cláudio Torres Arbe
Author-email: claudiotarbe@gmail.com
Classifier: Programming Language :: Python :: 3.8
Classifier: License :: OSI Approved :: MIT License
Classifier: Operating System :: OS Independent
Requires-Python: >=3.6
License-File: LICENSE
Requires-Dist: mysql-connector-python (==8.0.28)
